{"_ts":[1567386884],"_r":{"breakdown":{"html":{"bytes":[12152],"requests":[5]},"js":{"bytes":[254605],"requests":[14]},"css":{"bytes":[17321],"requests":[2]},"image":{"bytes":[276],"requests":[7]},"flash":{"bytes":[0],"requests":[0]},"font":{"bytes":[0],"requests":[0]},"video":{"bytes":[0],"requests":[0]},"other":{"bytes":[0],"requests":[1]}},"date":[1567386884],"domElements":[358],"domInteractive":[821],"firstPaint":[806.8000000058],"fullyLoaded":[2976],"id":["190902_25_e47998a7c275baab5987f862a002d2e6"],"loadTime":[1654],"render":[900],"SpeedIndex":[900],"TTFB":[457],"videoFrames":[[{"_i":"ms_000000.jpg","_t":0,"_vc":0},{"_i":"ms_000900.jpg","_t":900,"_vc":100}]],"visualComplete":[900],"lighthouse":[46],"pagespeed":[89]}}